setup.py
app/__init__.py
app/capacity_status.py
app/operation.py
fabricScalability.egg-info/PKG-INFO
fabricScalability.egg-info/SOURCES.txt
fabricScalability.egg-info/dependency_links.txt
fabricScalability.egg-info/requires.txt
fabricScalability.egg-info/top_level.txt